technical/__init__.py
technical/bouncyhouse.py
technical/candles.py
technical/indicator_helpers.py
technical/pivots_points.py
technical/qtpylib.py
technical/trendline.py
technical/util.py
technical/consensus/__init__.py
technical/consensus/consensus.py
technical/consensus/movingaverage.py
technical/consensus/oscillator.py
technical/consensus/summary.py
technical/indicators/__init__.py
technical/indicators/cycle_indicators.py
technical/indicators/indicators.py
technical/indicators/momentum.py
technical/indicators/overlap_studies.py
technical/indicators/price_transform.py
technical/indicators/volatility.py
technical/indicators/volume_indicators.py
technical/vendor/__init__.py
technical/vendor/qtpylib/__init__.py
technical/vendor/qtpylib/indicators.py
technical-1.5.3.dist-info/licenses/LICENSE
technical-1.5.3.dist-info/METADATA
technical-1.5.3.dist-info/WHEEL
technical-1.5.3.dist-info/top_level.txt
technical-1.5.3.dist-info/RECORD
